arab-bot-list/__init__.py
arab-bot-list/bots.py
arab_bot_list/__init__.py
arab_bot_list/bots.py
arab_bot_list-2.3.3.dist-info/METADATA
arab_bot_list-2.3.3.dist-info/WHEEL
arab_bot_list-2.3.3.dist-info/top_level.txt
arab_bot_list-2.3.3.dist-info/RECORD
