Metadata-Version: 2.1
Name: arab-bot-list
Version: 2.3.3
Summary: The official API package for Arab's bot list using Python 3
Home-page: https://github.com
Author: Jake
Author-email: jakediserin@gmail.com
License: MIT
Platform: UNKNOWN
Classifier: Programming Language :: Python :: 3
Classifier: License :: OSI Approved :: MIT License
Classifier: Operating System :: OS Independent
Requires-Python: >=3.6
Requires-Dist: requests
